{
   "CodeGenerationMode": 2,
   "ContextClassName": "AirlinesContext",
   "ContextNamespace": "Data",
   "DefaultDacpacSchema": null,
   "FilterSchemas": false,
   "IncludeConnectionString": false,
   "ModelNamespace": "Models",
   "OutputContextPath": "Data",
   "OutputPath": "Models",
   "ProjectRootNamespace": "Airlines.Apis",
   "Schemas": null,
   "SelectedHandlebarsLanguage": 0,
   "SelectedToBeGenerated": 0,
   "Tables": [
      {
         "Name": "[dbo].[AirPorts]",
         "ObjectType": 0
      },
      {
         "Name": "[dbo].[Books]",
         "ObjectType": 0
      },
      {
         "Name": "[dbo].[Flights]",
         "ObjectType": 0
      },
      {
         "Name": "[dbo].[Passagers]",
         "ObjectType": 0
      }
   ],
   "UiHint": "DESKTOP-9S6LNFS\\SQLEXPRESS.Airlines",
   "UseBoolPropertiesWithoutDefaultSql": false,
   "UseDatabaseNames": false,
   "UseDbContextSplitting": false,
   "UseFluentApiOnly": true,
   "UseHandleBars": false,
   "UseHierarchyId": false,
   "UseInflector": true,
   "UseLegacyPluralizer": false,
   "UseManyToManyEntity": false,
   "UseNoConstructor": false,
   "UseNoDefaultConstructor": false,
   "UseNoNavigations": false,
   "UseNoObjectFilter": false,
   "UseNodaTime": false,
   "UseNullableReferences": false,
   "UseSchemaFolders": false,
   "UseSpatial": false
}